calcyoulater2/__init__.py
calcyoulater2/unit_tests.py
calcyoulater2/static/img/calcyoulater.PNG
calcyoulater2/static/styles/style.css
calcyoulater2-2.0.0.dist-info/METADATA
calcyoulater2-2.0.0.dist-info/WHEEL
calcyoulater2-2.0.0.dist-info/top_level.txt
calcyoulater2-2.0.0.dist-info/RECORD
