Metadata-Version: 2.4
Name: calcyoulater2
Version: 2.0.0
Summary: A Flask-based calculator web app
Home-page: https://github.com/M-Nwanze/calcyoulater-pkg
Author: Mike
License: MIT
Classifier: Programming Language :: Python :: 3
Classifier: License :: OSI Approved :: MIT License
Classifier: Operating System :: OS Independent
Requires-Dist: flask
Dynamic: author
Dynamic: classifier
Dynamic: description
Dynamic: description-content-type
Dynamic: home-page
Dynamic: license
Dynamic: requires-dist
Dynamic: summary
